pympesa/__init__.py
pympesa/urls.py
pympesa-1.0.1.dist-info/DESCRIPTION.rst
pympesa-1.0.1.dist-info/METADATA
pympesa-1.0.1.dist-info/RECORD
pympesa-1.0.1.dist-info/WHEEL
pympesa-1.0.1.dist-info/metadata.json
pympesa-1.0.1.dist-info/top_level.txt
