Metadata-Version: 2.0
Name: pympesa
Version: 1.0.1
Summary: Mpesa rest api library
Home-page: https://github.com/pythias-io/pympesa
Author: Andrew Kamau
Author-email: andrew@pythias.io
License: MIT
Platform: UNKNOWN
Requires-Dist: requests
